mxtools/__init__.py
mxtools/_version.py
mxtools/eiger.py
mxtools/flyer.py
mxtools/governor.py
mxtools/handlers.py
mxtools/raster_flyer.py
mxtools/scans.py
mxtools/vector_program.py
mxtools/zebra.py
mxtools/tests/__init__.py
mxtools/tests/conftest.py
mxtools/tests/test_examples.py
mxtools-1.0.4.dist-info/AUTHORS.rst
mxtools-1.0.4.dist-info/LICENSE
mxtools-1.0.4.dist-info/METADATA
mxtools-1.0.4.dist-info/WHEEL
mxtools-1.0.4.dist-info/entry_points.txt
mxtools-1.0.4.dist-info/top_level.txt
mxtools-1.0.4.dist-info/RECORD
