Metadata-Version: 2.1
Name: mxtools
Version: 1.0.4
Summary: Common code for the MX beamlines at NSLS-II (AMX, FMX).
Home-page: https://github.com/NSLS-II-AMX/mxtools
Author: Jun Aishima
Author-email: jaishima@bnl.gov
License: BSD (3-clause)
Classifier: Development Status :: 2 - Pre-Alpha
Classifier: Natural Language :: English
Classifier: Programming Language :: Python :: 3
Requires-Python: >=3.7
License-File: LICENSE
License-File: AUTHORS.rst
Requires-Dist: bluesky
Requires-Dist: ophyd
Requires-Dist: pyepics
